[
  {
    "line": 1,
    "elements": [
      {
        "start_timestamp": "2022-11-04T13:17:34.759Z",
        "before": [
          {
            "result": {
              "duration": 13824505400,
              "status": "passed"
            },
            "match": {
              "location": "com.example.hook.AndroidDriverHook.before()"
            }
          }
        ],
        "line": 6,
        "name": "Open Login Page",
        "description": "",
        "id": "login;open-login-page",
        "after": [
          {
            "result": {
              "duration": 983126600,
              "status": "passed"
            },
            "match": {
              "location": "com.example.hook.AndroidDriverHook.after()"
            }
          }
        ],
        "type": "scenario",
        "keyword": "Scenario",
        "steps": [
          {
            "result": {
              "duration": 1499764900,
              "status": "passed"
            },
            "line": 7,
            "name": "I am in main page",
            "match": {
              "location": "com.example.steps.ProductStepDefinitions.iHaveOpenedTheMainPage()"
            },
            "keyword": "Given "
          },
          {
            "result": {
              "duration": 2243591000,
              "status": "passed"
            },
            "line": 8,
            "name": "I open login page",
            "match": {
              "location": "com.example.steps.LoginStepDefinitions.iOpenLoginPage()"
            },
            "keyword": "When "
          },
          {
            "result": {
              "duration": 250358500,
              "status": "passed"
            },
            "line": 9,
            "name": "login page id displayed",
            "match": {
              "location": "com.example.steps.LoginStepDefinitions.loginPageIdDisplayed()"
            },
            "keyword": "Then "
          }
        ]
      },
      {
        "start_timestamp": "2022-11-04T13:17:54.021Z",
        "before": [
          {
            "result": {
              "duration": 16501858000,
              "status": "passed"
            },
            "match": {
              "location": "com.example.hook.AndroidDriverHook.before()"
            }
          }
        ],
        "line": 20,
        "name": "Login with username and password",
        "description": "",
        "id": "login;login-with-username-and-password;;2",
        "after": [
          {
            "result": {
              "duration": 753204300,
              "status": "passed"
            },
            "match": {
              "location": "com.example.hook.AndroidDriverHook.after()"
            }
          }
        ],
        "type": "scenario",
        "keyword": "Scenario Outline",
        "steps": [
          {
            "result": {
              "duration": 1496141100,
              "status": "passed"
            },
            "line": 12,
            "name": "I am in login page",
            "match": {
              "location": "com.example.steps.LoginStepDefinitions.iAmInLoginPage()"
            },
            "keyword": "Given "
          },
          {
            "result": {
              "duration": 1009507100,
              "status": "passed"
            },
            "line": 13,
            "name": "I input \"thaur@mail.com\" email",
            "match": {
              "arguments": [
                {
                  "val": "\"thaur@mail.com\"",
                  "offset": 8
                }
              ],
              "location": "com.example.steps.LoginStepDefinitions.iInputEmail(java.lang.String)"
            },
            "keyword": "When "
          },
          {
            "result": {
              "duration": 1847049900,
              "status": "passed"
            },
            "line": 14,
            "name": "I input \"thaurn\" password",
            "match": {
              "arguments": [
                {
                  "val": "\"thaurn\"",
                  "offset": 8
                }
              ],
              "location": "com.example.steps.LoginStepDefinitions.iInputPassword(java.lang.String)"
            },
            "keyword": "And "
          },
          {
            "result": {
              "duration": 148601000,
              "status": "passed"
            },
            "line": 15,
            "name": "I click login button",
            "match": {
              "location": "com.example.steps.LoginStepDefinitions.iClickLoginButton()"
            },
            "keyword": "And "
          },
          {
            "result": {
              "duration": 3219422000,
              "status": "passed"
            },
            "line": 16,
            "name": "I get \"logged in\"",
            "match": {
              "arguments": [
                {
                  "val": "\"logged in\"",
                  "offset": 6
                }
              ],
              "location": "com.example.steps.LoginStepDefinitions.iGet(java.lang.String)"
            },
            "keyword": "Then "
          }
        ]
      },
      {
        "start_timestamp": "2022-11-04T13:18:19.081Z",
        "before": [
          {
            "result": {
              "duration": 12784056000,
              "status": "passed"
            },
            "match": {
              "location": "com.example.hook.AndroidDriverHook.before()"
            }
          }
        ],
        "line": 21,
        "name": "Login with username and password",
        "description": "",
        "id": "login;login-with-username-and-password;;3",
        "after": [
          {
            "result": {
              "duration": 599426700,
              "status": "passed"
            },
            "match": {
              "location": "com.example.hook.AndroidDriverHook.after()"
            }
          }
        ],
        "type": "scenario",
        "keyword": "Scenario Outline",
        "steps": [
          {
            "result": {
              "duration": 1210829700,
              "status": "passed"
            },
            "line": 12,
            "name": "I am in login page",
            "match": {
              "location": "com.example.steps.LoginStepDefinitions.iAmInLoginPage()"
            },
            "keyword": "Given "
          },
          {
            "result": {
              "duration": 1018910300,
              "status": "passed"
            },
            "line": 13,
            "name": "I input \"thaur@mail.com\" email",
            "match": {
              "arguments": [
                {
                  "val": "\"thaur@mail.com\"",
                  "offset": 8
                }
              ],
              "location": "com.example.steps.LoginStepDefinitions.iInputEmail(java.lang.String)"
            },
            "keyword": "When "
          },
          {
            "result": {
              "duration": 1532536800,
              "status": "passed"
            },
            "line": 14,
            "name": "I input \"pinto\" password",
            "match": {
              "arguments": [
                {
                  "val": "\"pinto\"",
                  "offset": 8
                }
              ],
              "location": "com.example.steps.LoginStepDefinitions.iInputPassword(java.lang.String)"
            },
            "keyword": "And "
          },
          {
            "result": {
              "duration": 1146003700,
              "status": "passed"
            },
            "line": 15,
            "name": "I click login button",
            "match": {
              "location": "com.example.steps.LoginStepDefinitions.iClickLoginButton()"
            },
            "keyword": "And "
          },
          {
            "result": {
              "duration": 2833981400,
              "status": "passed"
            },
            "line": 16,
            "name": "I get \"invalid error\"",
            "match": {
              "arguments": [
                {
                  "val": "\"invalid error\"",
                  "offset": 6
                }
              ],
              "location": "com.example.steps.LoginStepDefinitions.iGet(java.lang.String)"
            },
            "keyword": "Then "
          }
        ]
      },
      {
        "start_timestamp": "2022-11-04T13:18:40.235Z",
        "before": [
          {
            "result": {
              "duration": 20424545900,
              "status": "passed"
            },
            "match": {
              "location": "com.example.hook.AndroidDriverHook.before()"
            }
          }
        ],
        "line": 22,
        "name": "Login with username and password",
        "description": "",
        "id": "login;login-with-username-and-password;;4",
        "after": [
          {
            "result": {
              "duration": 884741700,
              "status": "passed"
            },
            "match": {
              "location": "com.example.hook.AndroidDriverHook.after()"
            }
          }
        ],
        "type": "scenario",
        "keyword": "Scenario Outline",
        "steps": [
          {
            "result": {
              "duration": 620088200,
              "status": "passed"
            },
            "line": 12,
            "name": "I am in login page",
            "match": {
              "location": "com.example.steps.LoginStepDefinitions.iAmInLoginPage()"
            },
            "keyword": "Given "
          },
          {
            "result": {
              "duration": 2340017000,
              "status": "passed"
            },
            "line": 13,
            "name": "I input \"user@mail.com\" email",
            "match": {
              "arguments": [
                {
                  "val": "\"user@mail.com\"",
                  "offset": 8
                }
              ],
              "location": "com.example.steps.LoginStepDefinitions.iInputEmail(java.lang.String)"
            },
            "keyword": "When "
          },
          {
            "result": {
              "duration": 2982115700,
              "status": "passed"
            },
            "line": 14,
            "name": "I input \"\" password",
            "match": {
              "arguments": [
                {
                  "val": "\"\"",
                  "offset": 8
                }
              ],
              "location": "com.example.steps.LoginStepDefinitions.iInputPassword(java.lang.String)"
            },
            "keyword": "And "
          },
          {
            "result": {
              "duration": 1276278900,
              "status": "passed"
            },
            "line": 15,
            "name": "I click login button",
            "match": {
              "location": "com.example.steps.LoginStepDefinitions.iClickLoginButton()"
            },
            "keyword": "And "
          },
          {
            "result": {
              "duration": 747903600,
              "status": "passed"
            },
            "line": 16,
            "name": "I get \"password error\"",
            "match": {
              "arguments": [
                {
                  "val": "\"password error\"",
                  "offset": 6
                }
              ],
              "location": "com.example.steps.LoginStepDefinitions.iGet(java.lang.String)"
            },
            "keyword": "Then "
          }
        ]
      },
      {
        "start_timestamp": "2022-11-04T13:19:09.577Z",
        "before": [
          {
            "result": {
              "duration": 15169696300,
              "status": "passed"
            },
            "match": {
              "location": "com.example.hook.AndroidDriverHook.before()"
            }
          }
        ],
        "line": 23,
        "name": "Login with username and password",
        "description": "",
        "id": "login;login-with-username-and-password;;5",
        "after": [
          {
            "result": {
              "duration": 631282200,
              "status": "passed"
            },
            "match": {
              "location": "com.example.hook.AndroidDriverHook.after()"
            }
          }
        ],
        "type": "scenario",
        "keyword": "Scenario Outline",
        "steps": [
          {
            "result": {
              "duration": 1218032600,
              "status": "passed"
            },
            "line": 12,
            "name": "I am in login page",
            "match": {
              "location": "com.example.steps.LoginStepDefinitions.iAmInLoginPage()"
            },
            "keyword": "Given "
          },
          {
            "result": {
              "duration": 1072447700,
              "status": "passed"
            },
            "line": 13,
            "name": "I input \"\" email",
            "match": {
              "arguments": [
                {
                  "val": "\"\"",
                  "offset": 8
                }
              ],
              "location": "com.example.steps.LoginStepDefinitions.iInputEmail(java.lang.String)"
            },
            "keyword": "When "
          },
          {
            "result": {
              "duration": 1130623500,
              "status": "passed"
            },
            "line": 14,
            "name": "I input \"nxxxae\" password",
            "match": {
              "arguments": [
                {
                  "val": "\"nxxxae\"",
                  "offset": 8
                }
              ],
              "location": "com.example.steps.LoginStepDefinitions.iInputPassword(java.lang.String)"
            },
            "keyword": "And "
          },
          {
            "result": {
              "duration": 1283355400,
              "status": "passed"
            },
            "line": 15,
            "name": "I click login button",
            "match": {
              "location": "com.example.steps.LoginStepDefinitions.iClickLoginButton()"
            },
            "keyword": "And "
          },
          {
            "result": {
              "duration": 121674300,
              "status": "passed"
            },
            "line": 16,
            "name": "I get \"email error\"",
            "match": {
              "arguments": [
                {
                  "val": "\"email error\"",
                  "offset": 6
                }
              ],
              "location": "com.example.steps.LoginStepDefinitions.iGet(java.lang.String)"
            },
            "keyword": "Then "
          }
        ]
      },
      {
        "start_timestamp": "2022-11-04T13:19:30.237Z",
        "before": [
          {
            "result": {
              "duration": 11706279700,
              "status": "passed"
            },
            "match": {
              "location": "com.example.hook.AndroidDriverHook.before()"
            }
          }
        ],
        "line": 24,
        "name": "Login with username and password",
        "description": "",
        "id": "login;login-with-username-and-password;;6",
        "after": [
          {
            "result": {
              "duration": 2009929900,
              "status": "passed"
            },
            "match": {
              "location": "com.example.hook.AndroidDriverHook.after()"
            }
          }
        ],
        "type": "scenario",
        "keyword": "Scenario Outline",
        "steps": [
          {
            "result": {
              "duration": 1863018600,
              "status": "passed"
            },
            "line": 12,
            "name": "I am in login page",
            "match": {
              "location": "com.example.steps.LoginStepDefinitions.iAmInLoginPage()"
            },
            "keyword": "Given "
          },
          {
            "result": {
              "duration": 1379933000,
              "status": "passed"
            },
            "line": 13,
            "name": "I input \"\" email",
            "match": {
              "arguments": [
                {
                  "val": "\"\"",
                  "offset": 8
                }
              ],
              "location": "com.example.steps.LoginStepDefinitions.iInputEmail(java.lang.String)"
            },
            "keyword": "When "
          },
          {
            "result": {
              "duration": 1077962600,
              "status": "passed"
            },
            "line": 14,
            "name": "I input \"\" password",
            "match": {
              "arguments": [
                {
                  "val": "\"\"",
                  "offset": 8
                }
              ],
              "location": "com.example.steps.LoginStepDefinitions.iInputPassword(java.lang.String)"
            },
            "keyword": "And "
          },
          {
            "result": {
              "duration": 261542500,
              "status": "passed"
            },
            "line": 15,
            "name": "I click login button",
            "match": {
              "location": "com.example.steps.LoginStepDefinitions.iClickLoginButton()"
            },
            "keyword": "And "
          },
          {
            "result": {
              "duration": 767879500,
              "status": "passed"
            },
            "line": 16,
            "name": "I get \"all error\"",
            "match": {
              "arguments": [
                {
                  "val": "\"all error\"",
                  "offset": 6
                }
              ],
              "location": "com.example.steps.LoginStepDefinitions.iGet(java.lang.String)"
            },
            "keyword": "Then "
          }
        ]
      }
    ],
    "name": "Login",
    "description": "  As a User\n  I want to login\n  So I can use the website",
    "id": "login",
    "keyword": "Feature",
    "uri": "file:src/test/resources/features/Login.feature",
    "tags": []
  },
  {
    "line": 1,
    "elements": [
      {
        "start_timestamp": "2022-11-04T13:19:49.427Z",
        "before": [
          {
            "result": {
              "duration": 23906038100,
              "status": "passed"
            },
            "match": {
              "location": "com.example.hook.AndroidDriverHook.before()"
            }
          }
        ],
        "line": 6,
        "name": "Logout",
        "description": "",
        "id": "logout;logout",
        "after": [
          {
            "result": {
              "duration": 1310767400,
              "status": "passed"
            },
            "match": {
              "location": "com.example.hook.AndroidDriverHook.after()"
            }
          }
        ],
        "type": "scenario",
        "keyword": "Scenario",
        "steps": [
          {
            "result": {
              "duration": 29909084400,
              "status": "passed"
            },
            "line": 7,
            "name": "I am logged in to the website",
            "match": {
              "location": "com.example.steps.LogoutStepDefinitions.iAmLoggedInToTheWebsite()"
            },
            "keyword": "Given "
          },
          {
            "result": {
              "duration": 711047300,
              "status": "passed"
            },
            "line": 8,
            "name": "I click logout button",
            "match": {
              "location": "com.example.steps.LogoutStepDefinitions.iClickLogoutButton()"
            },
            "keyword": "When "
          },
          {
            "result": {
              "duration": 215903200,
              "status": "passed"
            },
            "line": 9,
            "name": "I am logged out",
            "match": {
              "location": "com.example.steps.LogoutStepDefinitions.iAmLoggedOut()"
            },
            "keyword": "Then "
          }
        ]
      }
    ],
    "name": "Logout",
    "description": "  As a user\n  I want to logout\n  So I can stop checking out my cart",
    "id": "logout",
    "keyword": "Feature",
    "uri": "file:src/test/resources/features/Logout.feature",
    "tags": []
  },
  {
    "line": 2,
    "elements": [
      {
        "start_timestamp": "2022-11-04T13:20:45.587Z",
        "before": [
          {
            "result": {
              "duration": 12113438200,
              "status": "passed"
            },
            "match": {
              "location": "com.example.hook.AndroidDriverHook.before()"
            }
          }
        ],
        "line": 7,
        "name": "Add Product to Cart",
        "description": "",
        "id": "add-product-to-cart;add-product-to-cart",
        "after": [
          {
            "result": {
              "duration": 582594000,
              "status": "passed"
            },
            "match": {
              "location": "com.example.hook.AndroidDriverHook.after()"
            }
          }
        ],
        "type": "scenario",
        "keyword": "Scenario",
        "steps": [
          {
            "result": {
              "duration": 315734400,
              "status": "passed"
            },
            "line": 8,
            "name": "I am in main page",
            "match": {
              "location": "com.example.steps.ProductStepDefinitions.iHaveOpenedTheMainPage()"
            },
            "keyword": "Given "
          },
          {
            "result": {
              "duration": 4028809700,
              "status": "passed"
            },
            "line": 9,
            "name": "I click buy on one of the products",
            "match": {
              "location": "com.example.steps.ProductStepDefinitions.iClickBuyOnOneOfTheProducts()"
            },
            "keyword": "When "
          },
          {
            "result": {
              "duration": 159858000,
              "status": "passed"
            },
            "line": 10,
            "name": "My cart is filled",
            "match": {
              "location": "com.example.steps.ProductStepDefinitions.myCartIsFilled()"
            },
            "keyword": "Then "
          }
        ],
        "tags": [
          {
            "name": "@Product"
          }
        ]
      }
    ],
    "name": "Add Product to Cart",
    "description": "  As a user\n  I want to add product to cart\n  So I can buy the product",
    "id": "add-product-to-cart",
    "keyword": "Feature",
    "uri": "file:src/test/resources/features/Product.feature",
    "tags": [
      {
        "name": "@Product",
        "type": "Tag",
        "location": {
          "line": 1,
          "column": 1
        }
      }
    ]
  },
  {
    "line": 2,
    "elements": [
      {
        "start_timestamp": "2022-11-04T13:21:02.839Z",
        "before": [
          {
            "result": {
              "duration": 11697819600,
              "status": "passed"
            },
            "match": {
              "location": "com.example.hook.AndroidDriverHook.before()"
            }
          }
        ],
        "line": 7,
        "name": "Open Register Page",
        "description": "",
        "id": "register;open-register-page",
        "after": [
          {
            "result": {
              "duration": 522572800,
              "status": "passed"
            },
            "match": {
              "location": "com.example.hook.AndroidDriverHook.after()"
            }
          }
        ],
        "type": "scenario",
        "keyword": "Scenario",
        "steps": [
          {
            "result": {
              "duration": 2087279100,
              "status": "passed"
            },
            "line": 8,
            "name": "I open register page",
            "match": {
              "location": "com.example.steps.RegisterStepDefinitions.iOpenRegisterPage()"
            },
            "keyword": "When "
          },
          {
            "result": {
              "duration": 186497500,
              "status": "passed"
            },
            "line": 9,
            "name": "register page is displayed",
            "match": {
              "location": "com.example.steps.RegisterStepDefinitions.registerPageIsDisplayed()"
            },
            "keyword": "Then "
          }
        ],
        "tags": [
          {
            "name": "@Register"
          }
        ]
      },
      {
        "start_timestamp": "2022-11-04T13:21:17.367Z",
        "before": [
          {
            "result": {
              "duration": 12904740900,
              "status": "passed"
            },
            "match": {
              "location": "com.example.hook.AndroidDriverHook.before()"
            }
          }
        ],
        "line": 11,
        "name": "Register with new email",
        "description": "",
        "id": "register;register-with-new-email",
        "after": [
          {
            "result": {
              "duration": 570939600,
              "status": "passed"
            },
            "match": {
              "location": "com.example.hook.AndroidDriverHook.after()"
            }
          }
        ],
        "type": "scenario",
        "keyword": "Scenario",
        "steps": [
          {
            "result": {
              "duration": 2104756700,
              "status": "passed"
            },
            "line": 12,
            "name": "I open register page",
            "match": {
              "location": "com.example.steps.RegisterStepDefinitions.iOpenRegisterPage()"
            },
            "keyword": "Given "
          },
          {
            "result": {
              "duration": 1305470700,
              "status": "passed"
            },
            "line": 13,
            "name": "I input full name",
            "match": {
              "location": "com.example.steps.RegisterStepDefinitions.iInputFullName()"
            },
            "keyword": "When "
          },
          {
            "result": {
              "duration": 1655577400,
              "status": "passed"
            },
            "line": 14,
            "name": "I input new email",
            "match": {
              "location": "com.example.steps.RegisterStepDefinitions.iInputNewEmail()"
            },
            "keyword": "And "
          },
          {
            "result": {
              "duration": 1549331000,
              "status": "passed"
            },
            "line": 15,
            "name": "I input password",
            "match": {
              "location": "com.example.steps.RegisterStepDefinitions.iInputPassword()"
            },
            "keyword": "And "
          },
          {
            "result": {
              "duration": 1223683000,
              "status": "passed"
            },
            "line": 16,
            "name": "I click register",
            "match": {
              "location": "com.example.steps.RegisterStepDefinitions.iClickRegister()"
            },
            "keyword": "And "
          },
          {
            "result": {
              "duration": 2036137000,
              "status": "passed"
            },
            "line": 17,
            "name": "I am redirected to main page",
            "match": {
              "location": "com.example.steps.RegisterStepDefinitions.iAmRedirectedToMainPage()"
            },
            "keyword": "Then "
          }
        ],
        "tags": [
          {
            "name": "@Register"
          }
        ]
      },
      {
        "start_timestamp": "2022-11-04T13:21:40.773Z",
        "before": [
          {
            "result": {
              "duration": 10710711200,
              "status": "passed"
            },
            "match": {
              "location": "com.example.hook.AndroidDriverHook.before()"
            }
          }
        ],
        "line": 29,
        "name": "Register with username and email",
        "description": "",
        "id": "register;register-with-username-and-email;;2",
        "after": [
          {
            "result": {
              "duration": 632834600,
              "status": "passed"
            },
            "match": {
              "location": "com.example.hook.AndroidDriverHook.after()"
            }
          }
        ],
        "type": "scenario",
        "keyword": "Scenario Outline",
        "steps": [
          {
            "result": {
              "duration": 2580601900,
              "status": "passed"
            },
            "line": 20,
            "name": "I open register page",
            "match": {
              "location": "com.example.steps.RegisterStepDefinitions.iOpenRegisterPage()"
            },
            "keyword": "Given "
          },
          {
            "result": {
              "duration": 1385206900,
              "status": "passed"
            },
            "line": 21,
            "name": "I insert \"\" as full name",
            "match": {
              "arguments": [
                {
                  "val": "\"\"",
                  "offset": 9
                }
              ],
              "location": "com.example.steps.RegisterStepDefinitions.iInsertAsFullName(java.lang.String)"
            },
            "keyword": "When "
          },
          {
            "result": {
              "duration": 1507722800,
              "status": "passed"
            },
            "line": 22,
            "name": "I insert \"simail@mail.com\" as email",
            "match": {
              "arguments": [
                {
                  "val": "\"simail@mail.com\"",
                  "offset": 9
                }
              ],
              "location": "com.example.steps.RegisterStepDefinitions.iInsertAsEmail(java.lang.String)"
            },
            "keyword": "And "
          },
          {
            "result": {
              "duration": 1499975100,
              "status": "passed"
            },
            "line": 23,
            "name": "I insert \"mmail\" as password",
            "match": {
              "arguments": [
                {
                  "val": "\"mmail\"",
                  "offset": 9
                }
              ],
              "location": "com.example.steps.RegisterStepDefinitions.iInsertAsPassword(java.lang.String)"
            },
            "keyword": "And "
          },
          {
            "result": {
              "duration": 1193583600,
              "status": "passed"
            },
            "line": 24,
            "name": "I click register",
            "match": {
              "location": "com.example.steps.RegisterStepDefinitions.iClickRegister()"
            },
            "keyword": "And "
          },
          {
            "result": {
              "duration": 138630700,
              "status": "passed"
            },
            "line": 25,
            "name": "I get \"fullname\" error",
            "match": {
              "arguments": [
                {
                  "val": "\"fullname\"",
                  "offset": 6
                }
              ],
              "location": "com.example.steps.RegisterStepDefinitions.iGetError(java.lang.String)"
            },
            "keyword": "Then "
          }
        ],
        "tags": [
          {
            "name": "@Register"
          }
        ]
      },
      {
        "start_timestamp": "2022-11-04T13:22:00.552Z",
        "before": [
          {
            "result": {
              "duration": 12794076500,
              "status": "passed"
            },
            "match": {
              "location": "com.example.hook.AndroidDriverHook.before()"
            }
          }
        ],
        "line": 30,
        "name": "Register with username and email",
        "description": "",
        "id": "register;register-with-username-and-email;;3",
        "after": [
          {
            "result": {
              "duration": 605301100,
              "status": "passed"
            },
            "match": {
              "location": "com.example.hook.AndroidDriverHook.after()"
            }
          }
        ],
        "type": "scenario",
        "keyword": "Scenario Outline",
        "steps": [
          {
            "result": {
              "duration": 2119945400,
              "status": "passed"
            },
            "line": 20,
            "name": "I open register page",
            "match": {
              "location": "com.example.steps.RegisterStepDefinitions.iOpenRegisterPage()"
            },
            "keyword": "Given "
          },
          {
            "result": {
              "duration": 1208499200,
              "status": "passed"
            },
            "line": 21,
            "name": "I insert \"Sisimail\" as full name",
            "match": {
              "arguments": [
                {
                  "val": "\"Sisimail\"",
                  "offset": 9
                }
              ],
              "location": "com.example.steps.RegisterStepDefinitions.iInsertAsFullName(java.lang.String)"
            },
            "keyword": "When "
          },
          {
            "result": {
              "duration": 1627268500,
              "status": "passed"
            },
            "line": 22,
            "name": "I insert \"\" as email",
            "match": {
              "arguments": [
                {
                  "val": "\"\"",
                  "offset": 9
                }
              ],
              "location": "com.example.steps.RegisterStepDefinitions.iInsertAsEmail(java.lang.String)"
            },
            "keyword": "And "
          },
          {
            "result": {
              "duration": 1559866800,
              "status": "passed"
            },
            "line": 23,
            "name": "I insert \"mmail\" as password",
            "match": {
              "arguments": [
                {
                  "val": "\"mmail\"",
                  "offset": 9
                }
              ],
              "location": "com.example.steps.RegisterStepDefinitions.iInsertAsPassword(java.lang.String)"
            },
            "keyword": "And "
          },
          {
            "result": {
              "duration": 1344986100,
              "status": "passed"
            },
            "line": 24,
            "name": "I click register",
            "match": {
              "location": "com.example.steps.RegisterStepDefinitions.iClickRegister()"
            },
            "keyword": "And "
          },
          {
            "result": {
              "duration": 123667800,
              "status": "passed"
            },
            "line": 25,
            "name": "I get \"email\" error",
            "match": {
              "arguments": [
                {
                  "val": "\"email\"",
                  "offset": 6
                }
              ],
              "location": "com.example.steps.RegisterStepDefinitions.iGetError(java.lang.String)"
            },
            "keyword": "Then "
          }
        ],
        "tags": [
          {
            "name": "@Register"
          }
        ]
      },
      {
        "start_timestamp": "2022-11-04T13:22:21.962Z",
        "before": [
          {
            "result": {
              "duration": 10692627000,
              "status": "passed"
            },
            "match": {
              "location": "com.example.hook.AndroidDriverHook.before()"
            }
          }
        ],
        "line": 31,
        "name": "Register with username and email",
        "description": "",
        "id": "register;register-with-username-and-email;;4",
        "after": [
          {
            "result": {
              "duration": 540218000,
              "status": "passed"
            },
            "match": {
              "location": "com.example.hook.AndroidDriverHook.after()"
            }
          }
        ],
        "type": "scenario",
        "keyword": "Scenario Outline",
        "steps": [
          {
            "result": {
              "duration": 2268780400,
              "status": "passed"
            },
            "line": 20,
            "name": "I open register page",
            "match": {
              "location": "com.example.steps.RegisterStepDefinitions.iOpenRegisterPage()"
            },
            "keyword": "Given "
          },
          {
            "result": {
              "duration": 1266742200,
              "status": "passed"
            },
            "line": 21,
            "name": "I insert \"Sisimail\" as full name",
            "match": {
              "arguments": [
                {
                  "val": "\"Sisimail\"",
                  "offset": 9
                }
              ],
              "location": "com.example.steps.RegisterStepDefinitions.iInsertAsFullName(java.lang.String)"
            },
            "keyword": "When "
          },
          {
            "result": {
              "duration": 1645828400,
              "status": "passed"
            },
            "line": 22,
            "name": "I insert \"simail@mail.com\" as email",
            "match": {
              "arguments": [
                {
                  "val": "\"simail@mail.com\"",
                  "offset": 9
                }
              ],
              "location": "com.example.steps.RegisterStepDefinitions.iInsertAsEmail(java.lang.String)"
            },
            "keyword": "And "
          },
          {
            "result": {
              "duration": 1467219200,
              "status": "passed"
            },
            "line": 23,
            "name": "I insert \"\" as password",
            "match": {
              "arguments": [
                {
                  "val": "\"\"",
                  "offset": 9
                }
              ],
              "location": "com.example.steps.RegisterStepDefinitions.iInsertAsPassword(java.lang.String)"
            },
            "keyword": "And "
          },
          {
            "result": {
              "duration": 671174400,
              "status": "passed"
            },
            "line": 24,
            "name": "I click register",
            "match": {
              "location": "com.example.steps.RegisterStepDefinitions.iClickRegister()"
            },
            "keyword": "And "
          },
          {
            "result": {
              "duration": 613411900,
              "status": "passed"
            },
            "line": 25,
            "name": "I get \"password\" error",
            "match": {
              "arguments": [
                {
                  "val": "\"password\"",
                  "offset": 6
                }
              ],
              "location": "com.example.steps.RegisterStepDefinitions.iGetError(java.lang.String)"
            },
            "keyword": "Then "
          }
        ],
        "tags": [
          {
            "name": "@Register"
          }
        ]
      },
      {
        "start_timestamp": "2022-11-04T13:22:41.150Z",
        "before": [
          {
            "result": {
              "duration": 10975701400,
              "status": "passed"
            },
            "match": {
              "location": "com.example.hook.AndroidDriverHook.before()"
            }
          }
        ],
        "line": 32,
        "name": "Register with username and email",
        "description": "",
        "id": "register;register-with-username-and-email;;5",
        "after": [
          {
            "result": {
              "duration": 676225300,
              "status": "passed"
            },
            "match": {
              "location": "com.example.hook.AndroidDriverHook.after()"
            }
          }
        ],
        "type": "scenario",
        "keyword": "Scenario Outline",
        "steps": [
          {
            "result": {
              "duration": 2680390500,
              "status": "passed"
            },
            "line": 20,
            "name": "I open register page",
            "match": {
              "location": "com.example.steps.RegisterStepDefinitions.iOpenRegisterPage()"
            },
            "keyword": "Given "
          },
          {
            "result": {
              "duration": 1378803600,
              "status": "passed"
            },
            "line": 21,
            "name": "I insert \"Thaur Noh\" as full name",
            "match": {
              "arguments": [
                {
                  "val": "\"Thaur Noh\"",
                  "offset": 9
                }
              ],
              "location": "com.example.steps.RegisterStepDefinitions.iInsertAsFullName(java.lang.String)"
            },
            "keyword": "When "
          },
          {
            "result": {
              "duration": 1936873500,
              "status": "passed"
            },
            "line": 22,
            "name": "I insert \"thaur@mail.com\" as email",
            "match": {
              "arguments": [
                {
                  "val": "\"thaur@mail.com\"",
                  "offset": 9
                }
              ],
              "location": "com.example.steps.RegisterStepDefinitions.iInsertAsEmail(java.lang.String)"
            },
            "keyword": "And "
          },
          {
            "result": {
              "duration": 1603590600,
              "status": "passed"
            },
            "line": 23,
            "name": "I insert \"thaurn\" as password",
            "match": {
              "arguments": [
                {
                  "val": "\"thaurn\"",
                  "offset": 9
                }
              ],
              "location": "com.example.steps.RegisterStepDefinitions.iInsertAsPassword(java.lang.String)"
            },
            "keyword": "And "
          },
          {
            "result": {
              "duration": 1352360100,
              "status": "passed"
            },
            "line": 24,
            "name": "I click register",
            "match": {
              "location": "com.example.steps.RegisterStepDefinitions.iClickRegister()"
            },
            "keyword": "And "
          },
          {
            "result": {
              "duration": 2964718400,
              "status": "passed"
            },
            "line": 25,
            "name": "I get \"failed\" error",
            "match": {
              "arguments": [
                {
                  "val": "\"failed\"",
                  "offset": 6
                }
              ],
              "location": "com.example.steps.RegisterStepDefinitions.iGetError(java.lang.String)"
            },
            "keyword": "Then "
          }
        ],
        "tags": [
          {
            "name": "@Register"
          }
        ]
      },
      {
        "start_timestamp": "2022-11-04T13:23:04.756Z",
        "before": [
          {
            "result": {
              "duration": 11778928700,
              "status": "passed"
            },
            "match": {
              "location": "com.example.hook.AndroidDriverHook.before()"
            }
          }
        ],
        "line": 33,
        "name": "Register with username and email",
        "description": "",
        "id": "register;register-with-username-and-email;;6",
        "after": [
          {
            "result": {
              "duration": 551684600,
              "status": "passed"
            },
            "match": {
              "location": "com.example.hook.AndroidDriverHook.after()"
            }
          }
        ],
        "type": "scenario",
        "keyword": "Scenario Outline",
        "steps": [
          {
            "result": {
              "duration": 2148008400,
              "status": "passed"
            },
            "line": 20,
            "name": "I open register page",
            "match": {
              "location": "com.example.steps.RegisterStepDefinitions.iOpenRegisterPage()"
            },
            "keyword": "Given "
          },
          {
            "result": {
              "duration": 1315344000,
              "status": "passed"
            },
            "line": 21,
            "name": "I insert \"\" as full name",
            "match": {
              "arguments": [
                {
                  "val": "\"\"",
                  "offset": 9
                }
              ],
              "location": "com.example.steps.RegisterStepDefinitions.iInsertAsFullName(java.lang.String)"
            },
            "keyword": "When "
          },
          {
            "result": {
              "duration": 1641927700,
              "status": "passed"
            },
            "line": 22,
            "name": "I insert \"\" as email",
            "match": {
              "arguments": [
                {
                  "val": "\"\"",
                  "offset": 9
                }
              ],
              "location": "com.example.steps.RegisterStepDefinitions.iInsertAsEmail(java.lang.String)"
            },
            "keyword": "And "
          },
          {
            "result": {
              "duration": 1879899900,
              "status": "passed"
            },
            "line": 23,
            "name": "I insert \"\" as password",
            "match": {
              "arguments": [
                {
                  "val": "\"\"",
                  "offset": 9
                }
              ],
              "location": "com.example.steps.RegisterStepDefinitions.iInsertAsPassword(java.lang.String)"
            },
            "keyword": "And "
          },
          {
            "result": {
              "duration": 1236985500,
              "status": "passed"
            },
            "line": 24,
            "name": "I click register",
            "match": {
              "location": "com.example.steps.RegisterStepDefinitions.iClickRegister()"
            },
            "keyword": "And "
          },
          {
            "result": {
              "duration": 310186800,
              "status": "passed"
            },
            "line": 25,
            "name": "I get \"empty\" error",
            "match": {
              "arguments": [
                {
                  "val": "\"empty\"",
                  "offset": 6
                }
              ],
              "location": "com.example.steps.RegisterStepDefinitions.iGetError(java.lang.String)"
            },
            "keyword": "Then "
          }
        ],
        "tags": [
          {
            "name": "@Register"
          }
        ]
      }
    ],
    "name": "Register",
    "description": "  As a new user\n  I want to register\n  So that I can login",
    "id": "register",
    "keyword": "Feature",
    "uri": "file:src/test/resources/features/Register.feature",
    "tags": [
      {
        "name": "@Register",
        "type": "Tag",
        "location": {
          "line": 1,
          "column": 1
        }
      }
    ]
  }
]